setup.py
shinkenplugins/__init__.py
shinkenplugins.plugins.poller2livestatus.egg-info/PKG-INFO
shinkenplugins.plugins.poller2livestatus.egg-info/SOURCES.txt
shinkenplugins.plugins.poller2livestatus.egg-info/dependency_links.txt
shinkenplugins.plugins.poller2livestatus.egg-info/entry_points.txt
shinkenplugins.plugins.poller2livestatus.egg-info/namespace_packages.txt
shinkenplugins.plugins.poller2livestatus.egg-info/requires.txt
shinkenplugins.plugins.poller2livestatus.egg-info/top_level.txt
shinkenplugins/plugins/__init__.py
shinkenplugins/plugins/poller2livestatus/__init__.py
shinkenplugins/plugins/poller2livestatus/poller2livestatus.py